collections/tin_of_spam.py
collections_tin_of_spam-1.dist-info/WHEEL
collections_tin_of_spam-1.dist-info/METADATA
collections_tin_of_spam-1.dist-info/RECORD
