Metadata-Version: 2.4
Name: collections.tin_of_spam
Version: 1
Summary: Spam Spam Spam Egg and Spam
